hit/__init__.py
hit/auth.py
hit/clean.py
hit/cli.py
hit/clone.py
hit/conduit.py
hit/land.py
hit/message.py
hit/pull.py
hit/push.py
hit/py.typed
hit/utility.py
hit_cli-0.0.4.dist-info/LICENSE
hit_cli-0.0.4.dist-info/METADATA
hit_cli-0.0.4.dist-info/WHEEL
hit_cli-0.0.4.dist-info/entry_points.txt
hit_cli-0.0.4.dist-info/top_level.txt
hit_cli-0.0.4.dist-info/RECORD
