Metadata-Version: 2.1
Name: hit-cli
Version: 0.0.4
Summary: Graviti Github workflow CLI
Home-page: https://github.com/Graviti-AI/hit-cli
Author: Graviti
Author-email: pypi@graviti.com
License: MIT
Keywords: github,git,hit
Platform: UNKNOWN
Classifier: Development Status :: 2 - Pre-Alpha
Classifier: Intended Audience :: Developers
Classifier: License :: OSI Approved :: MIT License
Classifier: Operating System :: OS Independent
Classifier: Programming Language :: Python
Classifier: Programming Language :: Python :: 3
Classifier: Programming Language :: Python :: 3 :: Only
Classifier: Programming Language :: Python :: 3.6
Classifier: Programming Language :: Python :: 3.7
Classifier: Programming Language :: Python :: 3.8
Classifier: Programming Language :: Python :: 3.9
Classifier: Typing :: Typed
Requires-Python: >=3.6
Requires-Dist: click (>=7.0.0)
Requires-Dist: PyGithub (>=1.54.0)
